{"name":"project-prerana","path":"/tmp/codebase_city/project-prerana","buildings":[{"id":"aadhaar-prerana/vite.config.js","name":"vite.config.js","path":"aadhaar-prerana/vite.config.js","district_id":"district_6","position":{"x":-13.640716447832137,"y":0.0,"z":59.28363465841008},"dimensions":{"width":2.0,"height":1.0,"depth":2.0},"metrics":{"loc":7,"complexity":1,"churn":1,"age_days":5,"dependencies_in":0,"dependencies_out":0},"language":"javascript","summary":null,"decay_level":0.00684931506849315,"is_hotspot":false,"author":"Yashwanth Kamireddi","email":"yashwanthkamireddi@gmail.com"},{"id":"aadhaar-prerana/tailwind.config.js","name":"tailwind.config.js","path":"aadhaar-prerana/tailwind.config.js","district_id":"district_7","position":{"x":-31.44257767232968,"y":0.0,"z":-60.66583539027983},"dimensions":{"width":2.0,"height":1.0,"depth":2.0},"metrics":{"loc":26,"complexity":1,"churn":1,"age_days":5,"dependencies_in":0,"dependencies_out":0},"language":"javascript","summary":null,"decay_level":0.00684931506849315,"is_hotspot":false,"author":"Yashwanth Kamireddi","email":"yashwanthkamireddi@gmail.com"},{"id":"aadhaar-prerana/postcss.config.js","name":"postcss.config.js","path":"aadhaar-prerana/postcss.config.js","district_id":"district_8","position":{"x":64.27329364121717,"y":0.0,"z":25.71278187571202},"dimensions":{"width":2.0,"height":1.0,"depth":2.0},"metrics":{"loc":7,"complexity":1,"churn":1,"age_days":5,"dependencies_in":0,"dependencies_out":0},"language":"javascript","summary":null,"decay_level":0.00684931506849315,"is_hotspot":false,"author":"Yashwanth Kamireddi","email":"yashwanthkamireddi@gmail.com"},{"id":"aadhaar-prerana/backend/main.py","name":"main.py","path":"aadhaar-prerana/backend/main.py","district_id":"district_2","position":{"x":2.9516028401587016,"y":0.0,"z":-36.81104968474179},"dimensions":{"width":2.0,"height":7.2,"depth":2.0},"metrics":{"loc":175,"complexity":9,"churn":1,"age_days":5,"dependencies_in":0,"dependencies_out":6},"language":"python","summary":null,"decay_level":0.00684931506849315,"is_hotspot":false,"author":"Yashwanth Kamireddi","email":"yashwanthkamireddi@gmail.com"},{"id":"aadhaar-prerana/backend/api/routes.py","name":"routes.py","path":"aadhaar-prerana/backend/api/routes.py","district_id":"district_2","position":{"x":-0.33385885637116886,"y":0.0,"z":-35.15150427808221},"dimensions":{"width":3.71,"height":16.0,"depth":3.71},"metrics":{"loc":371,"complexity":20,"churn":1,"age_days":5,"dependencies_in":2,"dependencies_out":0},"language":"python","summary":null,"decay_level":0.00684931506849315,"is_hotspot":false,"author":"Yashwanth Kamireddi","email":"yashwanthkamireddi@gmail.com"},{"id":"aadhaar-prerana/backend/api/__init__.py","name":"__init__.py","path":"aadhaar-prerana/backend/api/__init__.py","district_id":"district_2","position":{"x":2.9598685922546464,"y":0.0,"z":-42.16631427974869},"dimensions":{"width":2.0,"height":1.6,"depth":2.0},"metrics":{"loc":5,"complexity":2,"churn":1,"age_days":5,"dependencies_in":0,"dependencies_out":1},"language":"python","summary":null,"decay_level":0.00684931506849315,"is_hotspot":false,"author":"Yashwanth Kamireddi","email":"yashwanthkamireddi@gmail.com"},{"id":"aadhaar-prerana/backend/config/settings.py","name":"settings.py","path":"aadhaar-prerana/backend/config/settings.py","district_id":"district_1","position":{"x":-18.707855269687673,"y":0.0,"z":18.731546947786835},"dimensions":{"width":2.0,"height":1.6,"depth":2.0},"metrics":{"loc":91,"complexity":2,"churn":1,"age_days":5,"dependencies_in":9,"dependencies_out":0},"language":"python","summary":null,"decay_level":0.00684931506849315,"is_hotspot":false,"author":"Yashwanth Kamireddi","email":"yashwanthkamireddi@gmail.com"},{"id":"aadhaar-prerana/backend/config/__init__.py","name":"__init__.py","path":"aadhaar-prerana/backend/config/__init__.py","district_id":"district_1","position":{"x":-21.09679534008163,"y":0.0,"z":21.287613980582332},"dimensions":{"width":2.0,"height":1.0,"depth":2.0},"metrics":{"loc":5,"complexity":1,"churn":1,"age_days":5,"dependencies_in":0,"dependencies_out":1},"language":"python","summary":null,"decay_level":0.00684931506849315,"is_hotspot":false,"author":"Yashwanth Kamireddi","email":"yashwanthkamireddi@gmail.com"},{"id":"aadhaar-prerana/backend/data_ingestion/pipeline.py","name":"pipeline.py","path":"aadhaar-prerana/backend/data_ingestion/pipeline.py","district_id":"district_4","position":{"x":-50.03100648191047,"y":0.0,"z":-6.3077259480406225},"dimensions":{"width":2.0,"height":19.200000000000003,"depth":2.0},"metrics":{"loc":157,"complexity":24,"churn":1,"age_days":5,"dependencies_in":1,"dependencies_out":0},"language":"python","summary":null,"decay_level":0.00684931506849315,"is_hotspot":false,"author":"Yashwanth Kamireddi","email":"yashwanthkamireddi@gmail.com"},{"id":"aadhaar-prerana/backend/data_ingestion/__init__.py","name":"__init__.py","path":"aadhaar-prerana/backend/data_ingestion/__init__.py","district_id":"district_4","position":{"x":-52.79018274817687,"y":0.0,"z":-4.1218951111175635},"dimensions":{"width":2.0,"height":1.0,"depth":2.0},"metrics":{"loc":5,"complexity":1,"churn":1,"age_days":5,"dependencies_in":0,"dependencies_out":1},"language":"python","summary":null,"decay_level":0.00684931506849315,"is_hotspot":false,"author":"Yashwanth Kamireddi","email":"yashwanthkamireddi@gmail.com"},{"id":"aadhaar-prerana/backend/engines/mobility_engine.py","name":"mobility_engine.py","path":"aadhaar-prerana/backend/engines/mobility_engine.py","district_id":"district_0","position":{"x":1.6369182294146205,"y":0.0,"z":0.4233340848669819},"dimensions":{"width":4.9,"height":25.0,"depth":4.9},"metrics":{"loc":490,"complexity":41,"churn":1,"age_days":5,"dependencies_in":2,"dependencies_out":3},"language":"python","summary":null,"decay_level":0.00684931506849315,"is_hotspot":false,"author":"Yashwanth Kamireddi","email":"yashwanthkamireddi@gmail.com"},{"id":"aadhaar-prerana/backend/engines/integrity_engine.py","name":"integrity_engine.py","path":"aadhaar-prerana/backend/engines/integrity_engine.py","district_id":"district_0","position":{"x":-1.3482082434332285,"y":0.0,"z":2.3832147152085854},"dimensions":{"width":5.52,"height":25.0,"depth":5.52},"metrics":{"loc":552,"complexity":61,"churn":1,"age_days":5,"dependencies_in":2,"dependencies_out":3},"language":"python","summary":null,"decay_level":0.00684931506849315,"is_hotspot":true,"author":"Yashwanth Kamireddi","email":"yashwanthkamireddi@gmail.com"},{"id":"aadhaar-prerana/backend/engines/genesis_engine.py","name":"genesis_engine.py","path":"aadhaar-prerana/backend/engines/genesis_engine.py","district_id":"district_0","position":{"x":1.712804330934266,"y":0.0,"z":-4.864310160716215},"dimensions":{"width":3.67,"height":25.0,"depth":3.67},"metrics":{"loc":367,"complexity":34,"churn":1,"age_days":5,"dependencies_in":3,"dependencies_out":3},"language":"python","summary":null,"decay_level":0.00684931506849315,"is_hotspot":false,"author":"Yashwanth Kamireddi","email":"yashwanthkamireddi@gmail.com"},{"id":"aadhaar-prerana/backend/engines/__init__.py","name":"__init__.py","path":"aadhaar-prerana/backend/engines/__init__.py","district_id":"district_0","position":{"x":3.991372364697267,"y":0.0,"z":3.900272525915266},"dimensions":{"width":2.0,"height":1.6,"depth":2.0},"metrics":{"loc":7,"complexity":2,"churn":1,"age_days":5,"dependencies_in":0,"dependencies_out":3},"language":"python","summary":null,"decay_level":0.00684931506849315,"is_hotspot":false,"author":"Yashwanth Kamireddi","email":"yashwanthkamireddi@gmail.com"},{"id":"aadhaar-prerana/backend/ml/train_mobility.py","name":"train_mobility.py","path":"aadhaar-prerana/backend/ml/train_mobility.py","district_id":"district_1","position":{"x":-18.801731336044064,"y":0.0,"z":13.274140534327604},"dimensions":{"width":2.0,"height":8.8,"depth":2.0},"metrics":{"loc":145,"complexity":11,"churn":1,"age_days":5,"dependencies_in":0,"dependencies_out":1},"language":"python","summary":null,"decay_level":0.00684931506849315,"is_hotspot":false,"author":"Yashwanth Kamireddi","email":"yashwanthkamireddi@gmail.com"},{"id":"aadhaar-prerana/backend/ml/train_integrity.py","name":"train_integrity.py","path":"aadhaar-prerana/backend/ml/train_integrity.py","district_id":"district_1","position":{"x":-14.611251534926156,"y":0.0,"z":23.950634988313993},"dimensions":{"width":2.48,"height":15.200000000000001,"depth":2.48},"metrics":{"loc":248,"complexity":19,"churn":1,"age_days":5,"dependencies_in":0,"dependencies_out":1},"language":"python","summary":null,"decay_level":0.00684931506849315,"is_hotspot":false,"author":"Yashwanth Kamireddi","email":"yashwanthkamireddi@gmail.com"},{"id":"aadhaar-prerana/backend/ml/train_genesis.py","name":"train_genesis.py","path":"aadhaar-prerana/backend/ml/train_genesis.py","district_id":"district_1","position":{"x":-25.839802272777664,"y":0.0,"z":17.273320689249662},"dimensions":{"width":2.83,"height":21.6,"depth":2.83},"metrics":{"loc":283,"complexity":27,"churn":1,"age_days":5,"dependencies_in":0,"dependencies_out":1},"language":"python","summary":null,"decay_level":0.00684931506849315,"is_hotspot":false,"author":"Yashwanth Kamireddi","email":"yashwanthkamireddi@gmail.com"},{"id":"aadhaar-prerana/backend/ml/__init__.py","name":"__init__.py","path":"aadhaar-prerana/backend/ml/__init__.py","district_id":"district_9","position":{"x":-72.16235781860031,"y":0.0,"z":26.83320374359841},"dimensions":{"width":2.0,"height":1.6,"depth":2.0},"metrics":{"loc":2,"complexity":2,"churn":1,"age_days":5,"dependencies_in":0,"dependencies_out":0},"language":"python","summary":null,"decay_level":0.00684931506849315,"is_hotspot":false,"author":"Yashwanth Kamireddi","email":"yashwanthkamireddi@gmail.com"},{"id":"aadhaar-prerana/backend/utils/statistics.py","name":"statistics.py","path":"aadhaar-prerana/backend/utils/statistics.py","district_id":"district_3","position":{"x":24.68706843059423,"y":0.0,"z":33.678502928202214},"dimensions":{"width":2.0,"height":11.200000000000001,"depth":2.0},"metrics":{"loc":140,"complexity":14,"churn":1,"age_days":5,"dependencies_in":1,"dependencies_out":0},"language":"python","summary":null,"decay_level":0.00684931506849315,"is_hotspot":false,"author":"Yashwanth Kamireddi","email":"yashwanthkamireddi@gmail.com"},{"id":"aadhaar-prerana/backend/utils/logger.py","name":"logger.py","path":"aadhaar-prerana/backend/utils/logger.py","district_id":"district_3","position":{"x":23.68325875001167,"y":0.0,"z":37.61970035080911},"dimensions":{"width":2.0,"height":6.4,"depth":2.0},"metrics":{"loc":87,"complexity":8,"churn":1,"age_days":5,"dependencies_in":2,"dependencies_out":1},"language":"python","summary":null,"decay_level":0.00684931506849315,"is_hotspot":false,"author":"Yashwanth Kamireddi","email":"yashwanthkamireddi@gmail.com"},{"id":"aadhaar-prerana/backend/utils/data_loader.py","name":"data_loader.py","path":"aadhaar-prerana/backend/utils/data_loader.py","district_id":"district_0","position":{"x":-5.903685380431401,"y":0.0,"z":-1.4435487804262208},"dimensions":{"width":2.0,"height":13.600000000000001,"depth":2.0},"metrics":{"loc":121,"complexity":17,"churn":1,"age_days":5,"dependencies_in":4,"dependencies_out":0},"language":"python","summary":null,"decay_level":0.00684931506849315,"is_hotspot":false,"author":"Yashwanth Kamireddi","email":"yashwanthkamireddi@gmail.com"},{"id":"aadhaar-prerana/backend/utils/cache.py","name":"cache.py","path":"aadhaar-prerana/backend/utils/cache.py","district_id":"district_0","position":{"x":7.130993598977318,"y":0.0,"z":-4.886581668948354},"dimensions":{"width":2.0,"height":12.8,"depth":2.0},"metrics":{"loc":94,"complexity":16,"churn":1,"age_days":5,"dependencies_in":4,"dependencies_out":0},"language":"python","summary":null,"decay_level":0.00684931506849315,"is_hotspot":false,"author":"Yashwanth Kamireddi","email":"yashwanthkamireddi@gmail.com"},{"id":"aadhaar-prerana/backend/utils/__init__.py","name":"__init__.py","path":"aadhaar-prerana/backend/utils/__init__.py","district_id":"district_3","position":{"x":26.02821894244288,"y":0.0,"z":29.65612309294802},"dimensions":{"width":2.0,"height":1.6,"depth":2.0},"metrics":{"loc":28,"complexity":2,"churn":1,"age_days":5,"dependencies_in":0,"dependencies_out":4},"language":"python","summary":null,"decay_level":0.00684931506849315,"is_hotspot":false,"author":"Yashwanth Kamireddi","email":"yashwanthkamireddi@gmail.com"},{"id":"aadhaar-prerana/scripts/prerana_analysis.py","name":"prerana_analysis.py","path":"aadhaar-prerana/scripts/prerana_analysis.py","district_id":"district_10","position":{"x":34.86439454959218,"y":0.0,"z":-70.62475095211363},"dimensions":{"width":2.99,"height":23.200000000000003,"depth":2.99},"metrics":{"loc":299,"complexity":29,"churn":1,"age_days":5,"dependencies_in":0,"dependencies_out":0},"language":"python","summary":null,"decay_level":0.00684931506849315,"is_hotspot":false,"author":"Yashwanth Kamireddi","email":"yashwanthkamireddi@gmail.com"},{"id":"aadhaar-prerana/src/main.jsx","name":"main.jsx","path":"aadhaar-prerana/src/main.jsx","district_id":"district_5","position":{"x":43.22137590439652,"y":0.0,"z":-33.53348854611275},"dimensions":{"width":2.0,"height":1.0,"depth":2.0},"metrics":{"loc":11,"complexity":1,"churn":1,"age_days":5,"dependencies_in":0,"dependencies_out":1},"language":"javascript","summary":null,"decay_level":0.00684931506849315,"is_hotspot":false,"author":"Yashwanth Kamireddi","email":"yashwanthkamireddi@gmail.com"},{"id":"aadhaar-prerana/src/App.jsx","name":"App.jsx","path":"aadhaar-prerana/src/App.jsx","district_id":"district_5","position":{"x":39.73230819258929,"y":0.0,"z":-32.077549154730534},"dimensions":{"width":2.0,"height":15.200000000000001,"depth":2.0},"metrics":{"loc":184,"complexity":19,"churn":3,"age_days":5,"dependencies_in":1,"dependencies_out":0},"language":"javascript","summary":null,"decay_level":0.00684931506849315,"is_hotspot":false,"author":"Yashwanth Kamireddi","email":"yashwanthkamireddi@gmail.com"},{"id":"aadhaar-prerana/src/components/Sidebar.jsx","name":"Sidebar.jsx","path":"aadhaar-prerana/src/components/Sidebar.jsx","district_id":"district_11","position":{"x":17.110547286151995,"y":0.0,"z":81.18800082466528},"dimensions":{"width":2.0,"height":2.4000000000000004,"depth":2.0},"metrics":{"loc":120,"complexity":3,"churn":2,"age_days":5,"dependencies_in":0,"dependencies_out":0},"language":"javascript","summary":null,"decay_level":0.00684931506849315,"is_hotspot":false,"author":"Yashwanth Kamireddi","email":"yashwanthkamireddi@gmail.com"},{"id":"aadhaar-prerana/src/components/MobilityMatrix.jsx","name":"MobilityMatrix.jsx","path":"aadhaar-prerana/src/components/MobilityMatrix.jsx","district_id":"district_12","position":{"x":-76.73883604549822,"y":0.0,"z":-40.41655859962611},"dimensions":{"width":2.0,"height":4.0,"depth":2.0},"metrics":{"loc":139,"complexity":5,"churn":3,"age_days":5,"dependencies_in":0,"dependencies_out":0},"language":"javascript","summary":null,"decay_level":0.00684931506849315,"is_hotspot":false,"author":"Yashwanth Kamireddi","email":"yashwanthkamireddi@gmail.com"},{"id":"aadhaar-prerana/src/components/IntegrityShield.jsx","name":"IntegrityShield.jsx","path":"aadhaar-prerana/src/components/IntegrityShield.jsx","district_id":"district_13","position":{"x":90.64121982683052,"y":0.0,"z":-11.037257404843643},"dimensions":{"width":2.0,"height":2.4000000000000004,"depth":2.0},"metrics":{"loc":148,"complexity":3,"churn":3,"age_days":5,"dependencies_in":0,"dependencies_out":0},"language":"javascript","summary":null,"decay_level":0.00684931506849315,"is_hotspot":false,"author":"Yashwanth Kamireddi","email":"yashwanthkamireddi@gmail.com"},{"id":"aadhaar-prerana/src/components/Header.jsx","name":"Header.jsx","path":"aadhaar-prerana/src/components/Header.jsx","district_id":"district_14","position":{"x":-49.303802815569846,"y":0.0,"z":77.54232051587609},"dimensions":{"width":2.0,"height":1.0,"depth":2.0},"metrics":{"loc":48,"complexity":1,"churn":2,"age_days":5,"dependencies_in":0,"dependencies_out":0},"language":"javascript","summary":null,"decay_level":0.00684931506849315,"is_hotspot":false,"author":"Yashwanth Kamireddi","email":"yashwanthkamireddi@gmail.com"},{"id":"aadhaar-prerana/src/components/GenesisTrigger.jsx","name":"GenesisTrigger.jsx","path":"aadhaar-prerana/src/components/GenesisTrigger.jsx","district_id":"district_15","position":{"x":-19.19607265101246,"y":0.0,"z":-91.98030857453108},"dimensions":{"width":2.0,"height":2.4000000000000004,"depth":2.0},"metrics":{"loc":158,"complexity":3,"churn":3,"age_days":5,"dependencies_in":0,"dependencies_out":0},"language":"javascript","summary":null,"decay_level":0.00684931506849315,"is_hotspot":false,"author":"Yashwanth Kamireddi","email":"yashwanthkamireddi@gmail.com"},{"id":"aadhaar-prerana/tests/test_engines.py","name":"test_engines.py","path":"aadhaar-prerana/tests/test_engines.py","district_id":"district_0","position":{"x":-0.7469426976638094,"y":0.0,"z":8.544398536894466},"dimensions":{"width":2.0,"height":10.4,"depth":2.0},"metrics":{"loc":145,"complexity":13,"churn":1,"age_days":5,"dependencies_in":0,"dependencies_out":1},"language":"python","summary":null,"decay_level":0.00684931506849315,"is_hotspot":false,"author":"Yashwanth Kamireddi","email":"yashwanthkamireddi@gmail.com"}],"districts":[{"id":"district_6","name":"Aadhaar Prerana","color":"#98D8C8","center":{"x":-12.857920662897845,"y":60.06643044334437},"boundary":[{"x":-42.59012852880955,"y":43.69934640300771},{"x":-17.759425735812833,"y":98.82274545312046},{"x":12.271890813417555,"y":56.198383592602},{"x":-0.37324620264727315,"y":37.2543606575553},{"x":-42.282693219477196,"y":43.15017364674628}],"building_count":1,"description":null},{"id":"district_7","name":"Aadhaar Prerana","color":"#F7DC6F","center":{"x":-30.484275495307664,"y":-59.70753321325782},"boundary":[{"x":-27.460794886494718,"y":-28.324556538106542},{"x":-0.5117201871221253,"y":-67.714524122793},{"x":-70.80681871683504,"y":-91.47510281012705},{"x":-47.591629833768046,"y":-35.48880210588327}],"building_count":1,"description":null},{"id":"district_8","name":"Aadhaar Prerana","color":"#BB8FCE","center":{"x":63.41401741146701,"y":24.853505645961867},"boundary":[{"x":37.2075144935222,"y":1.1151985706639067},{"x":53.03763223738177,"y":63.529059368401725},{"x":500.0,"y":482.7534270208935},{"x":500.0,"y":412.6328432380761},{"x":58.8154512092251,"y":-6.414471933435561}],"building_count":1,"description":null},{"id":"district_2","name":"Aadhaar Prerana","color":"#45B7D1","center":{"x":2.885228095391664,"y":-36.87742442950883},"boundary":[{"x":-27.460794886494718,"y":-28.324556538106542},{"x":-0.5117201871221253,"y":-67.714524122793},{"x":2.754589208625771,"y":-69.03345456225483},{"x":23.988324975162847,"y":-48.90309568946341},{"x":21.55855694473798,"y":-17.558932536306017},{"x":-22.23766400746015,"y":-19.467616336411833}],"building_count":3,"description":null},{"id":"district_1","name":"Aadhaar Prerana","color":"#4ECDC4","center":{"x":-18.66718230027142,"y":18.77221991720309},"boundary":[{"x":-23.74396175402314,"y":-6.622012146504814},{"x":4.518073167011057,"y":23.501161648360124},{"x":-0.37324620264727315,"y":37.2543606575553},{"x":-42.282693219477196,"y":43.15017364674628},{"x":-45.673520465579024,"y":20.891174283044492}],"building_count":5,"description":null},{"id":"district_4","name":"Aadhaar Prerana","color":"#FFEAA7","center":{"x":-49.630836102340865,"y":-5.907555568471017},"boundary":[{"x":-27.460794886494718,"y":-28.324556538106542},{"x":-47.591629833768046,"y":-35.48880210588327},{"x":-85.04583033924891,"y":-6.049004518200209},{"x":-45.673520465579024,"y":20.891174283044492},{"x":-23.74396175402314,"y":-6.622012146504814},{"x":-22.23766400746015,"y":-19.467616336411833}],"building_count":2,"description":null},{"id":"district_0","name":"Aadhaar Prerana","color":"#FF6B6B","center":{"x":1.2753793772835333,"y":0.06179523273589473},"boundary":[{"x":-22.23766400746015,"y":-19.467616336411833},{"x":21.55855694473798,"y":-17.558932536306017},{"x":36.572705678626825,"y":0.9523790339511038},{"x":4.518073167011057,"y":23.501161648360124},{"x":-23.74396175402314,"y":-6.622012146504814}],"building_count":7,"description":null},{"id":"district_9","name":"Aadhaar Prerana","color":"#85C1E9","center":{"x":-72.08580896507883,"y":26.90975259711989},"boundary":[{"x":-45.673520465579024,"y":20.891174283044492},{"x":-42.282693219477196,"y":43.15017364674628},{"x":-42.59012852880955,"y":43.69934640300771},{"x":-500.0,"y":341.46207381612754},{"x":-500.0,"y":59.059307938102066},{"x":-85.04583033924891,"y":-6.049004518200209}],"building_count":1,"description":null},{"id":"district_3","name":"Aadhaar Prerana","color":"#96CEB4","center":{"x":25.482656940710697,"y":34.47409143831868},"boundary":[{"x":-0.37324620264727315,"y":37.2543606575553},{"x":4.518073167011057,"y":23.501161648360124},{"x":36.572705678626825,"y":0.9523790339511038},{"x":37.2075144935222,"y":1.1151985706639067},{"x":53.03763223738177,"y":63.529059368401725},{"x":12.271890813417555,"y":56.198383592602}],"building_count":3,"description":null},{"id":"district_10","name":"Aadhaar Prerana","color":"#F8B500","center":{"x":34.87185569137221,"y":-70.6172898103336},"boundary":[{"x":23.988324975162847,"y":-48.90309568946341},{"x":2.754589208625771,"y":-69.03345456225483},{"x":284.71147116069056,"y":-500.0},{"x":500.0,"y":-499.2338914453631},{"x":85.08442503266181,"y":-62.3566738241141}],"building_count":1,"description":null},{"id":"district_5","name":"Aadhaar Prerana","color":"#DDA0DD","center":{"x":42.986012534104134,"y":-33.76885191640513},"boundary":[{"x":37.2075144935222,"y":1.1151985706639067},{"x":58.8154512092251,"y":-6.414471933435561},{"x":85.08442503266181,"y":-62.3566738241141},{"x":23.988324975162847,"y":-48.90309568946341},{"x":21.55855694473798,"y":-17.558932536306017},{"x":36.572705678626825,"y":0.9523790339511038}],"building_count":2,"description":null},{"id":"district_11","name":"Aadhaar Prerana","color":"#00CED1","center":{"x":17.08665223018958,"y":81.16410576870287},"boundary":[{"x":12.271890813417555,"y":56.198383592602},{"x":53.03763223738177,"y":63.529059368401725},{"x":500.0,"y":482.7534270208935},{"x":4.263256414560601e-14,"y":500.0},{"x":-76.20123569302407,"y":500.0},{"x":-17.759425735812833,"y":98.82274545312046}],"building_count":1,"description":null},{"id":"district_12","name":"Aadhaar Prerana","color":"#FF7F50","center":{"x":-76.81739448869425,"y":-40.49511704282214},"boundary":[{"x":-47.591629833768046,"y":-35.48880210588327},{"x":-70.80681871683504,"y":-91.47510281012705},{"x":-495.3454688612204,"y":-500.0},{"x":-500.0,"y":-4.263256414560601e-14},{"x":-500.0,"y":59.059307938102066},{"x":-85.04583033924891,"y":-6.049004518200209}],"building_count":1,"description":null},{"id":"district_13","name":"Aadhaar Prerana","color":"#9ACD32","center":{"x":89.97388237049245,"y":-11.704594861181722},"boundary":[{"x":58.8154512092251,"y":-6.414471933435561},{"x":500.0,"y":412.6328432380761},{"x":500.0,"y":-1.9539925233402755e-14},{"x":500.0,"y":-499.2338914453631},{"x":85.08442503266181,"y":-62.3566738241141}],"building_count":1,"description":null},{"id":"district_14","name":"Aadhaar Prerana","color":"#DA70D6","center":{"x":-50.03364147446683,"y":76.8124818569791},"boundary":[{"x":-42.59012852880955,"y":43.69934640300771},{"x":-500.0,"y":341.46207381612754},{"x":-76.20123569302407,"y":500.0},{"x":-17.759425735812833,"y":98.82274545312046}],"building_count":1,"description":null},{"id":"district_15","name":"Aadhaar Prerana","color":"#FF6B6B","center":{"x":-19.479793033689063,"y":-92.26402895720769},"boundary":[{"x":2.754589208625771,"y":-69.03345456225483},{"x":284.71147116069056,"y":-500.0},{"x":-4.263256414560601e-14,"y":-500.0},{"x":-495.3454688612204,"y":-500.0},{"x":-70.80681871683504,"y":-91.47510281012705},{"x":-0.5117201871221253,"y":-67.714524122793}],"building_count":1,"description":null}],"roads":[{"source":"aadhaar-prerana/backend/main.py","target":"aadhaar-prerana/backend/engines/genesis_engine.py","weight":1.0,"path":[],"is_cross_district":true},{"source":"aadhaar-prerana/backend/main.py","target":"aadhaar-prerana/backend/api/routes.py","weight":1.0,"path":[],"is_cross_district":false},{"source":"aadhaar-prerana/backend/main.py","target":"aadhaar-prerana/backend/utils/logger.py","weight":1.0,"path":[],"is_cross_district":true},{"source":"aadhaar-prerana/backend/main.py","target":"aadhaar-prerana/backend/config/settings.py","weight":1.0,"path":[],"is_cross_district":true},{"source":"aadhaar-prerana/backend/main.py","target":"aadhaar-prerana/backend/engines/integrity_engine.py","weight":1.0,"path":[],"is_cross_district":true},{"source":"aadhaar-prerana/backend/main.py","target":"aadhaar-prerana/backend/engines/mobility_engine.py","weight":1.0,"path":[],"is_cross_district":true},{"source":"aadhaar-prerana/backend/api/__init__.py","target":"aadhaar-prerana/backend/api/routes.py","weight":1.0,"path":[],"is_cross_district":false},{"source":"aadhaar-prerana/backend/config/__init__.py","target":"aadhaar-prerana/backend/config/settings.py","weight":1.0,"path":[],"is_cross_district":false},{"source":"aadhaar-prerana/backend/data_ingestion/__init__.py","target":"aadhaar-prerana/backend/data_ingestion/pipeline.py","weight":1.0,"path":[],"is_cross_district":false},{"source":"aadhaar-prerana/backend/engines/mobility_engine.py","target":"aadhaar-prerana/backend/utils/data_loader.py","weight":1.0,"path":[],"is_cross_district":false},{"source":"aadhaar-prerana/backend/engines/mobility_engine.py","target":"aadhaar-prerana/backend/config/settings.py","weight":1.0,"path":[],"is_cross_district":true},{"source":"aadhaar-prerana/backend/engines/mobility_engine.py","target":"aadhaar-prerana/backend/utils/cache.py","weight":1.0,"path":[],"is_cross_district":false},{"source":"aadhaar-prerana/backend/engines/integrity_engine.py","target":"aadhaar-prerana/backend/utils/data_loader.py","weight":1.0,"path":[],"is_cross_district":false},{"source":"aadhaar-prerana/backend/engines/integrity_engine.py","target":"aadhaar-prerana/backend/config/settings.py","weight":1.0,"path":[],"is_cross_district":true},{"source":"aadhaar-prerana/backend/engines/integrity_engine.py","target":"aadhaar-prerana/backend/utils/cache.py","weight":1.0,"path":[],"is_cross_district":false},{"source":"aadhaar-prerana/backend/engines/genesis_engine.py","target":"aadhaar-prerana/backend/utils/data_loader.py","weight":1.0,"path":[],"is_cross_district":false},{"source":"aadhaar-prerana/backend/engines/genesis_engine.py","target":"aadhaar-prerana/backend/config/settings.py","weight":1.0,"path":[],"is_cross_district":true},{"source":"aadhaar-prerana/backend/engines/genesis_engine.py","target":"aadhaar-prerana/backend/utils/cache.py","weight":1.0,"path":[],"is_cross_district":false},{"source":"aadhaar-prerana/backend/engines/__init__.py","target":"aadhaar-prerana/backend/engines/genesis_engine.py","weight":1.0,"path":[],"is_cross_district":false},{"source":"aadhaar-prerana/backend/engines/__init__.py","target":"aadhaar-prerana/backend/engines/integrity_engine.py","weight":1.0,"path":[],"is_cross_district":false},{"source":"aadhaar-prerana/backend/engines/__init__.py","target":"aadhaar-prerana/backend/engines/mobility_engine.py","weight":1.0,"path":[],"is_cross_district":false},{"source":"aadhaar-prerana/backend/ml/train_mobility.py","target":"aadhaar-prerana/backend/config/settings.py","weight":1.0,"path":[],"is_cross_district":false},{"source":"aadhaar-prerana/backend/ml/train_integrity.py","target":"aadhaar-prerana/backend/config/settings.py","weight":1.0,"path":[],"is_cross_district":false},{"source":"aadhaar-prerana/backend/ml/train_genesis.py","target":"aadhaar-prerana/backend/config/settings.py","weight":1.0,"path":[],"is_cross_district":false},{"source":"aadhaar-prerana/backend/utils/logger.py","target":"aadhaar-prerana/backend/config/settings.py","weight":1.0,"path":[],"is_cross_district":true},{"source":"aadhaar-prerana/backend/utils/__init__.py","target":"aadhaar-prerana/backend/utils/statistics.py","weight":1.0,"path":[],"is_cross_district":false},{"source":"aadhaar-prerana/backend/utils/__init__.py","target":"aadhaar-prerana/backend/utils/cache.py","weight":1.0,"path":[],"is_cross_district":true},{"source":"aadhaar-prerana/backend/utils/__init__.py","target":"aadhaar-prerana/backend/utils/data_loader.py","weight":1.0,"path":[],"is_cross_district":true},{"source":"aadhaar-prerana/backend/utils/__init__.py","target":"aadhaar-prerana/backend/utils/logger.py","weight":1.0,"path":[],"is_cross_district":false},{"source":"aadhaar-prerana/src/main.jsx","target":"aadhaar-prerana/src/App.jsx","weight":1.0,"path":[],"is_cross_district":false},{"source":"aadhaar-prerana/tests/test_engines.py","target":"aadhaar-prerana/backend/engines/genesis_engine.py","weight":1.0,"path":[],"is_cross_district":false}],"stats":{"total_files":32,"total_loc":4665,"total_districts":16,"total_dependencies":31,"hotspots":1},"metadata":{"num_files":32,"num_directories":16,"languages":{},"layer_violations":[{"source":"aadhaar-prerana/backend/utils/__init__.py","target":"aadhaar-prerana/backend/utils/data_loader.py","sourceLayer":"util","targetLayer":"data","message":"Layer Violation: util should not import data"}],"duplicates":[],"issues":{"circular_dependencies":[],"god_objects":[],"orphans":["aadhaar-prerana/vite.config.js","aadhaar-prerana/tailwind.config.js","aadhaar-prerana/postcss.config.js","aadhaar-prerana/backend/ml/__init__.py","aadhaar-prerana/scripts/prerana_analysis.py","aadhaar-prerana/src/components/Sidebar.jsx","aadhaar-prerana/src/components/MobilityMatrix.jsx","aadhaar-prerana/src/components/IntegrityShield.jsx","aadhaar-prerana/src/components/Header.jsx","aadhaar-prerana/src/components/GenesisTrigger.jsx"],"highly_coupled":[],"large_files":[]},"health":{"score":98,"grade":"A"}}}